CHANGES.txt
CONTRIBUTING.txt
MANIFEST.in
README.rst
bootstrap.py
buildout-cache.cfg
buildout.cfg
requirements-4.2.txt
requirements-4.3.txt
requirements-5.0.txt
requirements-5.1.txt
setup.py
travis.cfg
conf/test-3.3.x.cfg
conf/test-4.1.x.cfg
conf/test-4.2.x.cfg
docs/LICENSE.GPL
docs/LICENSE.txt
src/collective/__init__.py
src/collective.listingviews.egg-info/PKG-INFO
src/collective.listingviews.egg-info/SOURCES.txt
src/collective.listingviews.egg-info/dependency_links.txt
src/collective.listingviews.egg-info/entry_points.txt
src/collective.listingviews.egg-info/namespace_packages.txt
src/collective.listingviews.egg-info/not-zip-safe
src/collective.listingviews.egg-info/requires.txt
src/collective.listingviews.egg-info/top_level.txt
src/collective/listingviews/__init__.py
src/collective/listingviews/configure.zcml
src/collective/listingviews/interfaces.py
src/collective/listingviews/profiles.zcml
src/collective/listingviews/testing.py
src/collective/listingviews/tests.py
src/collective/listingviews/utils.py
src/collective/listingviews/validation.py
src/collective/listingviews/vocabularies.py
src/collective/listingviews/browser/__init__.py
src/collective/listingviews/browser/configure.zcml
src/collective/listingviews/browser/files/style.css
src/collective/listingviews/browser/portlets/__init__.py
src/collective/listingviews/browser/portlets/configure.zcml
src/collective/listingviews/browser/portlets/portlets.py
src/collective/listingviews/browser/portlets/templates/listing-portlet.pt
src/collective/listingviews/browser/views/__init__.py
src/collective/listingviews/browser/views/base.py
src/collective/listingviews/browser/views/basic.py
src/collective/listingviews/browser/views/collection.py
src/collective/listingviews/browser/views/configure.zcml
src/collective/listingviews/browser/views/controlpanel.py
src/collective/listingviews/browser/views/listing_view.py
src/collective/listingviews/browser/views/templates/layout.pt
src/collective/listingviews/profiles/default/collective.listingviews.txt
src/collective/listingviews/profiles/default/controlpanel.xml
src/collective/listingviews/profiles/default/cssregistry.xml
src/collective/listingviews/profiles/default/metadata.xml
src/collective/listingviews/profiles/default/portlets.xml
src/collective/listingviews/profiles/uninstall/collective.listingviews.uninstall.txt
src/collective/listingviews/profiles/uninstall/metadata.xml
