Metadata-Version: 1.1
Name: collective.listingviews
Version: 1.0.1
Summary: Listing views
Home-page: http://github.com/collective/collective.listingviews
Author: Pretaweb
Author-email: support@pretaweb.com
License: GPL
Keywords: Plone Python TTW
Platform: UNKNOWN
Classifier: Framework :: Plone
Classifier: Framework :: Plone :: 4.2
Classifier: Framework :: Plone :: 4.3
Classifier: Framework :: Plone :: 5.0
Classifier: Framework :: Plone :: 5.1
Classifier: Programming Language :: Python
Classifier: Topic :: Software Development :: Libraries :: Python Modules
